atu/__init__.py
atu/base.py
atu-0.0.1.dist-info/LICENSE
atu-0.0.1.dist-info/METADATA
atu-0.0.1.dist-info/WHEEL
atu-0.0.1.dist-info/top_level.txt
atu-0.0.1.dist-info/RECORD
